prerender/__init__.py
prerender/app.py
prerender/chromerdp.py
prerender/cli.py
prerender/constants.py
prerender/exceptions.py
prerender/mhtml.py
prerender/prerender.py
prerender/utils.py
prerender/cache/__init__.py
prerender/cache/base.py
prerender/cache/disk.py
prerender/cache/dummy.py
prerender/cache/s3.py
prerender-0.10.0.dist-info/METADATA
prerender-0.10.0.dist-info/RECORD
prerender-0.10.0.dist-info/WHEEL
prerender-0.10.0.dist-info/entry_points.txt
prerender-0.10.0.dist-info/top_level.txt
