Metadata-Version: 2.1
Name: prerender
Version: 0.10.0
Summary: Render JavaScript-rendered page as HTML using headless Chrome
Home-page: UNKNOWN
Author: messense
Author-email: messense@icloud.com
License: UNKNOWN
Keywords: prerender
Platform: UNKNOWN
Classifier: Programming Language :: Python
Classifier: Programming Language :: Python :: 3.6
Classifier: Programming Language :: Python :: Implementation :: CPython
Classifier: Topic :: Utilities
Provides-Extra: diskcache
Provides-Extra: s3
Requires-Dist: websockets
Requires-Dist: aiohttp
Requires-Dist: ujson
Requires-Dist: sanic (>=0.7)
Requires-Dist: sanic-compress
Requires-Dist: raven
Requires-Dist: raven-aiohttp
Requires-Dist: diskcache
Requires-Dist: httpagentparser
Requires-Dist: pyfailsafe
Provides-Extra: diskcache
Requires-Dist: diskcache; extra == 'diskcache'
Provides-Extra: s3
Requires-Dist: minio (>=3.0.0); extra == 's3'
